task3/ram.sv
module ram  #(
    parameter  ADDRESS_WIDTH = 9,
               DATA_WIDTH = 8

)(
    input logic                           clk,
    input logic                           wr_en,
    input logic                           rd_en,
    input logic  [ADDRESS_WIDTH-1:0]      wr_addr,
    input logic  [ADDRESS_WIDTH-1:0]      rd_addr,
    input logic  [DATA_WIDTH-1:0]         din,
    input logic  [DATA_WIDTH-1:0]         offset,
    output logic  [DATA_WIDTH-1:0]         dout 
);

logic  [DATA_WIDTH-1:0] ram_array [2**ADDRESS_WIDTH-1:0];

always_ff @(posedge clk) begin
    if (wr_en == 1'b1)
    ram_array[wr_addr + offset] <= din;
    if (rd_en == 1'b1)
       // output is synchronous
       dout <= ram_array     [rd_addr];
end
endmodule

task3/counter.sv
module counter #(
    parameter WIDTH = 9
)(
    //interface signals
    input  logic             clk,        //clock
    input  logic             rst,        //reset
    input  logic             en,         //counter enable 
    input logic [WIDTH-1:0] incr,      //count output
    output logic [WIDTH-1:0] count      //count output
   
);

always_ff @ (posedge clk)
    if (rst) count <= {WIDTH{1'b0}};
   
    else  count <= count + (en ?  incr : 0);

endmodule

task3/sigdelay.sv
module sinegen #(
    parameter  A_WIDTH = 9,
               D_WIDTH = 8
)(
    // interface signals
    input  logic                  clk,     //clock
    input  logic                  rst,     //reset
    input  logic                  en,      //enable
    input  logic          [A_WIDTH-1:0]         offset,
    input  logic  [D_WIDTH-1:0]   incr,    // increment for addr counter
    input logic                           wr,
    input logic                           rd,
    input logic  [D_WIDTH-1:0]         mic_signal,

    output logic  [D_WIDTH-1:0]   delayed_signal     // output data

    
);

logic  [A_WIDTH-1:0]      rd_addr;


counter addCounter (
    .clk(clk),
    .rst(rst),
    .en(en),
    .incr(incr),
    .count(rd_addr)
);

ram sineRam(
    .clk(clk),
    .din(mic_signal),
    .offset(offset),
    .wr_addr(rd_addr),
    .rd_addr(rd_addr),
    .wr_en(wr),
    .rd_en(rd),
    .dout(delayed_signal)
);

endmodule

task3/sigdelay.vcd
$version Generated by VerilatedVcd $end
$date Fri Nov  4 19:21:57 2022 $end
$timescale 1ps $end

 $scope module TOP $end
  $var wire  1 # clk $end
  $var wire  8 + delayed_signal [7:0] $end
  $var wire  1 % en $end
  $var wire  8 ' incr [7:0] $end
  $var wire  8 * mic_signal [7:0] $end
  $var wire  9 & offset [8:0] $end
  $var wire  1 ) rd $end
  $var wire  1 $ rst $end
  $var wire  1 ( wr $end
  $scope module sinegen $end
   $var wire 32 / A_WIDTH [31:0] $end
   $var wire 32 0 D_WIDTH [31:0] $end
   $var wire  1 # clk $end
   $var wire  8 + delayed_signal [7:0] $end
   $var wire  1 % en $end
   $var wire  8 ' incr [7:0] $end
   $var wire  8 * mic_signal [7:0] $end
   $var wire  9 & offset [8:0] $end
   $var wire  1 ) rd $end
   $var wire  9 , rd_addr [8:0] $end
   $var wire  1 $ rst $end
   $var wire  1 ( wr $end
   $scope module addCounter $end
    $var wire 32 / WIDTH [31:0] $end
    $var wire  1 # clk $end
    $var wire  9 , count [8:0] $end
    $var wire  1 % en $end
    $var wire  9 - incr [8:0] $end
    $var wire  1 $ rst $end
   $upscope $end
   $scope module sineRam $end
    $var wire 32 / ADDRESS_WIDTH [31:0] $end
    $var wire 32 0 DATA_WIDTH [31:0] $end
    $var wire  1 # clk $end
    $var wire  8 * din [7:0] $end
    $var wire  8 + dout [7:0] $end
    $var wire  8 . offset [7:0] $end
    $var wire  9 , rd_addr [8:0] $end
    $var wire  1 ) rd_en $end
    $var wire  9 , wr_addr [8:0] $end
    $var wire  1 ( wr_en $end
   $upscope $end
  $upscope $end
 $upscope $end
$enddefinitions $end


#0
1#
0$
0%
b001000000 &
b00000000 '
1(
1)
b00000000 *
b00000000 +
b000000000 ,
b000000000 -
b01000000 .
b00000000000000000000000000001001 /
b00000000000000000000000000001000 0
#1
0#
#2
1#
b000110011 &
b01100011 *
b00110011 .
#3
0#
#4
1#
b01100111 *
#5
0#
#6
1#
#7
0#
#8
1#
#9
0#
#10
1#
b01100110 *
#11
0#
#12
1#
b01101011 *
#13
0#
#14
1#
b01101000 *
#15
0#
#16
1#
#17
0#
#18
1#
b01100111 *
#19
0#
#20
1#
#21
0#
#22
1#
b01100100 *
#23
0#
#24
1#
b01101000 *
#25
0#
#26
1#
b01100100 *
#27
0#
#28
1#
#29
0#
#30
1#
#31
0#
#32
1#
#33
0#
#34
1#
b01100001 *
#35
0#
#36
1#
b01100000 *
#37
0#
#38
1#
b01011111 *
#39
0#
#40
1#
b01100000 *
#41
0#
#42
1#
b01011111 *
#43
0#
#44
1#
b01100001 *
#45
0#
#46
1#
b01100000 *
#47
0#
#48
1#
b01011110 *
#49
0#
#50
1#
b01011111 *
#51
0#
#52
1#
b01011101 *
#53
0#
#54
1#
b01011100 *
#55
0#
#56
1#
b01011011 *
#57
0#
#58
1#
#59
0#
#60
1#
b01011100 *
#61
0#
#62
1#
b01011011 *
#63
0#
#64
1#
b01011010 *
#65
0#
#66
1#
b01011011 *
#67
0#
#68
1#
b01011110 *
#69
0#
#70
1#
b01011101 *
#71
0#
#72
1#
b01100001 *
#73
0#
#74
1#
#75
0#
#76
1#
#77
0#
#78
1#
b01100100 *
#79
0#
#80
1#
#81
0#
#82
1#
#83
0#
#84
1#
b01100110 *
#85
0#
#86
1#
b01101000 *
#87
0#
#88
1#
b01101001 *
#89
0#
#90
1#
b01100110 *
#91
0#
#92
1#
b01100111 *
#93
0#
#94
1#
#95
0#
#96
1#
b01100110 *
#97
0#
#98
1#
#99
0#
#100
1#
b01100111 *
#101
0#
#102
1#
#103
0#
#104
1#
#105
0#
#106
1#
#107
0#
#108
1#
b01101000 *
#109
0#
#110
1#
#111
0#
#112
1#
b01100100 *
#113
0#
#114
1#
#115
0#
#116
1#
#117
0#
#118
1#
b01100001 *
#119
0#
#120
1#
b01100011 *
#121
0#
#122
1#
b01100010 *
#123
0#
#124
1#
b01100101 *
#125
0#
#126
1#
b01100111 *
#127
0#
#128
1#
b01100101 *
#129
0#
#130
1#
b01100111 *
#131
0#
#132
1#
b01100101 *
#133
0#
#134
1#
#135
0#
#136
1#
b01101000 *
#137
0#
#138
1#
b01101011 *
#139
0#
#140
1#
b01101100 *
#141
0#
#142
1#
b01110000 *
#143
0#
#144
1#
b01110001 *
#145
0#
#146
1#
#147
0#
#148
1#
b01110100 *
#149
0#
#150
1#
b01110001 *
#151
0#
#152
1#
#153
0#
#154
1#
b01110010 *
#155
0#
#156
1#
#157
0#
#158
1#
b01101111 *
#159
0#
#160
1#
b01110010 *
#161
0#
#162
1#
b01110011 *
#163
0#
#164
1#
b01110001 *
#165
0#
#166
1#
b01110011 *
#167
0#
#168
1#
b01110010 *
#169
0#
#170
1#
b01110001 *
#171
0#
#172
1#
b01110010 *
#173
0#
#174
1#
#175
0#
#176
1#
b01110000 *
#177
0#
#178
1#
b01110010 *
#179
0#
#180
1#
b01110001 *
#181
0#
#182
1#
b01101111 *
#183
0#
#184
1#
b01101110 *
#185
0#
#186
1#
b01101111 *
#187
0#
#188
1#
b01101101 *
#189
0#
#190
1#
b01101100 *
#191
0#
#192
1#
b01101111 *
#193
0#
#194
1#
b01101100 *
#195
0#
#196
1#
b01101011 *
#197
0#
#198
1#
#199
0#
#200
1#
b01101000 *
#201
0#
#202
1#
b01101001 *
#203
0#
#204
1#
b01101011 *
#205
0#
#206
1#
b01101001 *
#207
0#
#208
1#
b01101011 *
#209
0#
#210
1#
b01101111 *
#211
0#
#212
1#
b01101010 *
#213
0#
#214
1#
b01110000 *
#215
0#
#216
1#
b01101111 *
#217
0#
#218
1#
b01101110 *
#219
0#
#220
1#
#221
0#
#222
1#
b01101111 *
#223
0#
#224
1#
#225
0#
#226
1#
b01110011 *
#227
0#
#228
1#
b01110010 *
#229
0#
#230
1#
b01110011 *
#231
0#
#232
1#
b01110001 *
#233
0#
#234
1#
#235
0#
#236
1#
b01101110 *
#237
0#
#238
1#
#239
0#
#240
1#
b01101100 *
#241
0#
#242
1#
#243
0#
#244
1#
b01101010 *
#245
0#
#246
1#
b01101000 *
#247
0#
#248
1#
b01100111 *
#249
0#
#250
1#
b01100001 *
#251
0#
#252
1#
b01100000 *
#253
0#
#254
1#
b01011101 *
#255
0#
#256
1#
b01011100 *
#257
0#
#258
1#
b01011110 *
#259
0#
#260
1#
#261
0#
#262
1#
b01011111 *
#263
0#
#264
1#
b01100011 *
#265
0#
#266
1#
b01100010 *
#267
0#
#268
1#
b01011111 *
#269
0#
#270
1#
b01100000 *
#271
0#
#272
1#
b01100010 *
#273
0#
#274
1#
b01100011 *
#275
0#
#276
1#
b01100111 *
#277
0#
#278
1#
b01101001 *
#279
0#
#280
1#
b01101101 *
#281
0#
#282
1#
b01101111 *
#283
0#
#284
1#
b01101100 *
#285
0#
#286
1#
b01101011 *
#287
0#
#288
1#
b01101101 *
#289
0#
#290
1#
b01101011 *
#291
0#
#292
1#
#293
0#
#294
1#
#295
0#
#296
1#
b01101000 *
#297
0#
#298
1#
#299
0#
#300
1#
b01100100 *
#301
0#
#302
1#
b01100011 *
#303
0#
#304
1#
b01100100 *
#305
0#
#306
1#
b01100010 *
#307
0#
#308
1#
b01100001 *
#309
0#
#310
1#
b01100010 *
#311
0#
#312
1#
b01100001 *
#313
0#
#314
1#
b01100010 *
#315
0#
#316
1#
b01011111 *
#317
0#
#318
1#
b01011110 *
#319
0#
#320
1#
b01011111 *
#321
0#
#322
1#
b01100000 *
#323
0#
#324
1#
b01100010 *
#325
0#
#326
1#
#327
0#
#328
1#
b01100101 *
#329
0#
#330
1#
b01100100 *
#331
0#
#332
1#
b01100111 *
#333
0#
#334
1#
b01100100 *
#335
0#
#336
1#
b01100111 *
#337
0#
#338
1#
b01101000 *
#339
0#
#340
1#
b01101011 *
#341
0#
#342
1#
b01101001 *
#343
0#
#344
1#
b01101110 *
#345
0#
#346
1#
b01101100 *
#347
0#
#348
1#
b01101110 *
#349
0#
#350
1#
b01101101 *
#351
0#
#352
1#
#353
0#
#354
1#
b01101100 *
#355
0#
#356
1#
b01101101 *
#357
0#
#358
1#
b01101100 *
#359
0#
#360
1#
b01101101 *
#361
0#
#362
1#
b01101110 *
#363
0#
#364
1#
b01101101 *
#365
0#
#366
1#
b01101001 *
#367
0#
#368
1#
#369
0#
#370
1#
b01100110 *
#371
0#
#372
1#
b01100101 *
#373
0#
#374
1#
b01100100 *
#375
0#
#376
1#
b01100101 *
#377
0#
#378
1#
b01100100 *
#379
0#
#380
1#
#381
0#
#382
1#
b01100101 *
#383
0#
#384
1#
b01100110 *
#385
0#
#386
1#
b01100111 *
#387
0#
#388
1#
b01100110 *
#389
0#
#390
1#
#391
0#
#392
1#
b01100111 *
#393
0#
#394
1#
b01101001 *
#395
0#
#396
1#
b01100101 *
#397
0#
#398
1#
b01101001 *
#399
0#
#400
1#
b01101000 *
#401
0#
#402
1#
b01101010 *
#403
0#
#404
1#
#405
0#
#406
1#
#407
0#
#408
1#
b01101011 *
#409
0#
#410
1#
#411
0#
#412
1#
#413
0#
#414
1#
b01101000 *
#415
0#
#416
1#
#417
0#
#418
1#
b01101001 *
#419
0#
#420
1#
b01101000 *
#421
0#
#422
1#
b01101010 *
#423
0#
#424
1#
b01100111 *
#425
0#
#426
1#
b01101000 *
#427
0#
#428
1#
#429
0#
#430
1#
#431
0#
#432
1#
b01100111 *
#433
0#
#434
1#
b01100101 *
#435
0#
#436
1#
b01100111 *
#437
0#
#438
1#
b01100100 *
#439
0#
#440
1#
b01100101 *
#441
0#
#442
1#
b01100011 *
#443
0#
#444
1#
#445
0#
#446
1#
b01100100 *
#447
0#
#448
1#
b01100110 *
#449
0#
#450
1#
b01100101 *
#451
0#
#452
1#
b01100110 *
#453
0#
#454
1#
b01100111 *
#455
0#
#456
1#
b01101000 *
#457
0#
#458
1#
b01100111 *
#459
0#
#460
1#
b01101001 *
#461
0#
#462
1#
b01101010 *
#463
0#
#464
1#
b01101011 *
#465
0#
#466
1#
b01100111 *
#467
0#
#468
1#
b01100110 *
#469
0#
#470
1#
b01101010 *
#471
0#
#472
1#
b01100111 *
#473
0#
#474
1#
b01101000 *
#475
0#
#476
1#
#477
0#
#478
1#
b01100101 *
#479
0#
#480
1#
b01100111 *
#481
0#
#482
1#
b01100101 *
#483
0#
#484
1#
b01100100 *
#485
0#
#486
1#
b01100110 *
#487
0#
#488
1#
b01100101 *
#489
0#
#490
1#
b01100111 *
#491
0#
#492
1#
#493
0#
#494
1#
b01101000 *
#495
0#
#496
1#
b01101010 *
#497
0#
#498
1#
b01101000 *
#499
0#
#500
1#
b01101001 *
#501
0#
#502
1#
b01101010 *
#503
0#
#504
1#
b01101000 *
#505
0#
#506
1#
b01101001 *
#507
0#
#508
1#
b01101000 *
#509
0#
#510
1#
b01100111 *
#511
0#
#512
1#
#513
0#
#514
1#
b01101000 *
#515
0#
#516
1#
b01101001 *
#517
0#
#518
1#
b01101011 *
#519
0#
#520
1#
#521
0#
#522
1#
b01101100 *
#523
0#
#524
1#
b01101111 *
#525
0#
#526
1#
#527
0#
#528
1#
b01101110 *
#529
0#
#530
1#
b01101101 *
#531
0#
#532
1#
#533
0#
#534
1#
b01101011 *
#535
0#
#536
1#
#537
0#
#538
1#
b01101101 *
#539
0#
#540
1#
b01101011 *
#541
0#
#542
1#
b01101100 *
#543
0#
#544
1#
b01101101 *
#545
0#
#546
1#
b01101001 *
#547
0#
#548
1#
#549
0#
#550
1#
b01100111 *
#551
0#
#552
1#
#553
0#
#554
1#
b01101001 *
#555
0#
#556
1#
#557
0#
#558
1#
b01101010 *
#559
0#
#560
1#
b01101000 *
#561
0#
#562
1#
b01101011 *
#563
0#
#564
1#
b01101001 *
#565
0#
#566
1#
b01101010 *
#567
0#
#568
1#
#569
0#
#570
1#
b01100111 *
#571
0#
#572
1#
#573
0#
#574
1#
b01100110 *
#575
0#
#576
1#
b01101001 *
#577
0#
#578
1#
b01101000 *
#579
0#
#580
1#
b01101010 *
#581
0#
#582
1#
b01101001 *
#583
0#
#584
1#
b01101011 *
#585
0#
#586
1#
b01101010 *
#587
0#
#588
1#
#589
0#
#590
1#
b01101100 *
#591
0#
#592
1#
b01101110 *
#593
0#
#594
1#
b01101111 *
#595
0#
#596
1#
#597
0#
#598
1#
b01101101 *
#599
0#
#600
1#
b01101100 *
#601
0#
#602
1#
b01101101 *
#603
0#
#604
1#
b01101100 *
#605
0#
#606
1#
b01101111 *
#607
0#
#608
1#
#609
0#
#610
1#
b01101101 *
#611
0#
#612
1#
b01110000 *
#613
0#
#614
1#
#615
0#
#616
1#
b01101110 *
#617
0#
#618
1#
b01101100 *
#619
0#
#620
1#
#621
0#
#622
1#
b01101011 *
#623
0#
#624
1#
b01101001 *
#625
0#
#626
1#
b01101011 *
#627
0#
#628
1#
b01101010 *
#629
0#
#630
1#
b01101001 *
#631
0#
#632
1#
b01100111 *
#633
0#
#634
1#
b01101000 *
#635
0#
#636
1#
#637
0#
#638
1#
#639
0#
#640
1#
b01101100 *
#641
0#
#642
1#
#643
0#
#644
1#
b01101101 *
#645
0#
#646
1#
b01101100 *
#647
0#
#648
1#
b01101011 *
#649
0#
#650
1#
b01101111 *
#651
0#
#652
1#
b01101101 *
#653
0#
#654
1#
b01101100 *
#655
0#
#656
1#
b01101110 *
#657
0#
#658
1#
b01110000 *
#659
0#
#660
1#
b01110011 *
#661
0#
#662
1#
b01110010 *
#663
0#
#664
1#
b01101110 *
#665
0#
#666
1#
b01101111 *
#667
0#
#668
1#
b01101110 *
#669
0#
#670
1#
b01101100 *
#671
0#
#672
1#
#673
0#
#674
1#
#675
0#
#676
1#
b01101001 *
#677
0#
#678
1#
#679
0#
#680
1#
#681
0#
#682
1#
b01101011 *
#683
0#
#684
1#
b01101010 *
#685
0#
#686
1#
#687
0#
#688
1#
b000110001 &
b01101001 *
b00110001 .
#689
0#
#690
1#
b000101110 &
b00101110 .
#691
0#
#692
1#
b000101101 &
b01101011 *
b00101101 .
#693
0#
#694
1#
b01101010 *
#695
0#
#696
1#
b01101001 *
#697
0#
#698
1#
b01101000 *
#699
0#
#700
1#
#701
0#
#702
1#
#703
0#
#704
1#
#705
0#
#706
1#
b01101010 *
#707
0#
#708
1#
b000101000 &
b00101000 .
#709
0#
#710
1#
b000100110 &
b01101111 *
b00100110 .
#711
0#
#712
1#
b01101101 *
#713
0#
#714
1#
b01101010 *
#715
0#
#716
1#
b01101011 *
#717
0#
#718
1#
#719
0#
#720
1#
b01101001 *
#721
0#
#722
1#
b01100111 *
#723
0#
#724
1#
b000100101 &
b01101001 *
b00100101 .
#725
0#
#726
1#
b000100010 &
b01100111 *
b00100010 .
#727
0#
#728
1#
b000011111 &
b01100110 *
b00011111 .
#729
0#
#730
1#
#731
0#
#732
1#
b01100100 *
#733
0#
#734
1#
b01100010 *
#735
0#
#736
1#
#737
0#
#738
1#
b01100100 *
#739
0#
#740
1#
#741
0#
#742
1#
b01100011 *
#743
0#
#744
1#
b01100110 *
#745
0#
#746
1#
b01100010 *
#747
0#
#748
1#
b000011101 &
b01100001 *
b00011101 .
#749
0#
#750
1#
b000011000 &
b01100000 *
b00011000 .
#751
0#
#752
1#
b01011111 *
#753
0#
#754
1#
b01100010 *
#755
0#
#756
1#
b01100011 *
#757
0#
#758
1#
b01100101 *
#759
0#
#760
1#
b01101000 *
#761
0#
#762
1#
#763
0#
#764
1#
b01100111 *
#765
0#
#766
1#
b01100110 *
#767
0#
#768
1#
b000010110 &
b01100011 *
b00010110 .
#769
0#
#770
1#
b000010011 &
b00010011 .
#771
0#
#772
1#
b01100101 *
#773
0#
#774
1#
#775
0#
#776
1#
b01100011 *
#777
0#
#778
1#
b01100100 *
#779
0#
#780
1#
b01100101 *
#781
0#
#782
1#
b01101000 *
#783
0#
#784
1#
b01100111 *
#785
0#
#786
1#
b01101010 *
#787
0#
#788
1#
b000010010 &
b01100111 *
b00010010 .
#789
0#
#790
1#
b000010000 &
b01101001 *
b00010000 .
#791
0#
#792
1#
b000001100 &
b00001100 .
#793
0#
#794
1#
b01101000 *
#795
0#
#796
1#
b01101001 *
#797
0#
#798
1#
#799
0#
#800
1#
b01101000 *
#801
0#
#802
1#
b01101001 *
#803
0#
#804
1#
b01101000 *
#805
0#
#806
1#
#807
0#
#808
1#
b01100111 *
#809
0#
#810
1#
b000001011 &
b01101000 *
b00001011 .
#811
0#
#812
1#
b000001000 &
b00001000 .
#813
0#
#814
1#
b000000110 &
b01100111 *
b00000110 .
#815
0#
#816
1#
b01101001 *
#817
0#
#818
1#
b01101100 *
#819
0#
#820
1#
b01101101 *
#821
0#
#822
1#
#823
0#
#824
1#
b01101110 *
#825
0#
#826
1#
#827
0#
#828
1#
b01110000 *
#829
0#
#830
1#
b01110010 *
#831
0#
#832
1#
b01101110 *
#833
0#
#834
1#
b01110000 *
#835
0#
#836
1#
b01101111 *
#837
0#
#838
1#
b000000101 &
b00000101 .
#839
0#
#840
1#
#841
0#
#842
1#
b01110010 *
#843
0#
#844
1#
b01110001 *
#845
0#
#846
1#
b01110010 *
#847
0#
#848
1#
b000000100 &
b01110011 *
b00000100 .
#849
0#
#850
1#
b01110000 *
#851
0#
#852
1#
b01101110 *
#853
0#
#854
1#
b01110000 *
#855
0#
#856
1#
b01101110 *
#857
0#
#858
1#
b01101111 *
#859
0#
#860
1#
b01110000 *
#861
0#
#862
1#
b01110010 *
#863
0#
#864
1#
b01110011 *
#865
0#
#866
1#
#867
0#
#868
1#
b01110000 *
#869
0#
#870
1#
b000000011 &
b01110010 *
b00000011 .
#871
0#
#872
1#
b01110001 *
#873
0#
#874
1#
b01110000 *
#875
0#
#876
1#
b01110001 *
#877
0#
#878
1#
b01110010 *
#879
0#
#880
1#
b01110011 *
#881
0#
#882
1#
b000000010 &
b01110001 *
b00000010 .
#883
0#
#884
1#
b01101110 *
#885
0#
#886
1#
b01110001 *
#887
0#
#888
1#
b01101111 *
#889
0#
#890
1#
b000000001 &
b01101100 *
b00000001 .
#891
0#
#892
1#
#893
0#
#894
1#
b01101011 *
#895
0#
#896
1#
b01101110 *
#897
0#
#898
1#
#899
0#
#900
1#
b01101101 *
#901
0#
#902
1#
#903
0#
#904
1#
b01101100 *
#905
0#
#906
1#
b01101010 *
#907
0#
#908
1#
b01101001 *
#909
0#
#910
1#
#911
0#
#912
1#
#913
0#
#914
1#
#915
0#
#916
1#
b01101000 *
#917
0#
#918
1#
b01101001 *
#919
0#
#920
1#
#921
0#
#922
1#
b01101000 *
#923
0#
#924
1#
b000000000 &
b01100110 *
b00000000 .
#925
0#
#926
1#
b01101000 *
#927
0#
#928
1#
b01100100 *
b01100110 +
#929
0#
#930
1#
b01100101 *
b01101000 +
#931
0#
#932
1#
b01100110 *
b01100100 +
#933
0#
#934
1#
b01100100 *
b01100101 +
#935
0#
#936
1#
b01100111 *
b01100110 +
#937
0#
#938
1#
b01100110 *
b01100100 +
#939
0#
#940
1#
b01100100 *
b01100111 +
#941
0#
#942
1#
b01100101 *
b01100110 +
#943
0#
#944
1#
b01100100 *
b01100100 +
#945
0#
#946
1#
b01100011 *
b01100101 +
#947
0#
#948
1#
b01100100 +
#949
0#
#950
1#
b01100001 *
b01100011 +
#951
0#
#952
1#
b01100010 *
#953
0#
#954
1#
b01011111 *
b01100001 +
#955
0#
#956
1#
b01100010 *
b01100010 +
#957
0#
#958
1#
b01011111 +
#959
0#
#960
1#
b01100101 *
b01100010 +
#961
0#
#962
1#
b01100111 *
#963
0#
#964
1#
b01100101 +
#965
0#
#966
1#
b01101000 *
b01100111 +
#967
0#
#968
1#
b01100111 *
#969
0#
#970
1#
b01101010 *
b01101000 +
#971
0#
#972
1#
b01101001 *
b01100111 +
#973
0#
#974
1#
b01100111 *
b01101010 +
#975
0#
#976
1#
b01101000 *
b01101001 +
#977
0#
#978
1#
b01100110 *
b01100111 +
#979
0#
#980
1#
b01100100 *
b01101000 +
#981
0#
#982
1#
b01100101 *
b01100110 +
#983
0#
#984
1#
b01100010 *
b01100100 +
#985
0#
#986
1#
b01100000 *
b01100101 +
#987
0#
#988
1#
b01011110 *
b01100010 +
#989
0#
#990
1#
b01011111 *
b01100000 +
#991
0#
#992
1#
b01011110 +
#993
0#
#994
1#
b01100010 *
b01011111 +
#995
0#
#996
1#
b01100001 *
#997
0#
#998
1#
b01100100 *
b01100010 +
#999
0#
#1000
1#
b01100011 *
b01100001 +
#1001
0#
#1002
1#
b01100110 *
b01100100 +
#1003
0#
#1004
1#
b01100111 *
b01100011 +
#1005
0#
#1006
1#
b01100101 *
b01100110 +
#1007
0#
#1008
1#
b01100100 *
b01100111 +
#1009
0#
#1010
1#
b01100010 *
b01100101 +
#1011
0#
#1012
1#
b01100011 *
b01100100 +
#1013
0#
#1014
1#
b01100010 *
b01100010 +
#1015
0#
#1016
1#
b01100101 *
b01100011 +
#1017
0#
#1018
1#
b01100010 +
#1019
0#
#1020
1#
b01100111 *
b01100101 +
#1021
0#
#1022
1#
b01101001 *
#1023
0#
#1024
1#
b01101100 *
b01100111 +
#1025
0#
#1026
1#
b01101000 *
b01101001 +
#1027
0#
#1028
1#
b01100111 *
b01101100 +
#1029
0#
#1030
1#
b01101010 *
b01101000 +
#1031
0#
#1032
1#
b01100111 +
#1033
0#
#1034
1#
b01101101 *
b01101010 +
#1035
0#
#1036
1#
b01101011 *
#1037
0#
#1038
1#
b01101100 *
b01101101 +
#1039
0#
#1040
1#
b01101110 *
b01101011 +
#1041
0#
#1042
1#
b01101100 +
#1043
0#
#1044
1#
b01101101 *
b01101110 +
#1045
0#
#1046
1#
b01101111 *
#1047
0#
#1048
1#
b01101110 *
b01101101 +
#1049
0#
#1050
1#
b01101101 *
b01101111 +
#1051
0#
#1052
1#
b01101110 *
b01101110 +
#1053
0#
#1054
1#
b01101101 *
b01101101 +
#1055
0#
#1056
1#
b01101110 +
#1057
0#
#1058
1#
b01101101 +
#1059
0#
#1060
1#
#1061
0#
#1062
1#
#1063
0#
#1064
1#
b01101010 *
#1065
0#
#1066
1#
b01101101 *
#1067
0#
#1068
1#
b01101010 +
#1069
0#
#1070
1#
b01101111 *
b01101101 +
#1071
0#
#1072
1#
b01101110 *
#1073
0#
#1074
1#
b01110001 *
b01101111 +
#1075
0#
#1076
1#
b01101110 +
#1077
0#
#1078
1#
b01110001 +
#1079
0#
#1080
1#
b01110011 *
#1081
0#
#1082
1#
b01110010 *
#1083
0#
#1084
1#
b01110000 *
b01110011 +
#1085
0#
#1086
1#
b01110010 +
#1087
0#
#1088
1#
b01110010 *
b01110000 +
#1089
0#
#1090
1#
b01101111 *
#1091
0#
#1092
1#
b01110000 *
b01110010 +
#1093
0#
#1094
1#
b01101111 *
b01101111 +
#1095
0#
#1096
1#
b01110011 *
b01110000 +
#1097
0#
#1098
1#
b01110110 *
b01101111 +
#1099
0#
#1100
1#
b01110100 *
b01110011 +
#1101
0#
#1102
1#
b01110010 *
b01110110 +
#1103
0#
#1104
1#
b01101111 *
b01110100 +
#1105
0#
#1106
1#
b01101101 *
b01110010 +
#1107
0#
#1108
1#
b01101110 *
b01101111 +
#1109
0#
#1110
1#
b01101111 *
b01101101 +
#1111
0#
#1112
1#
b01101101 *
b01101110 +
#1113
0#
#1114
1#
b01101111 *
b01101111 +
#1115
0#
#1116
1#
b01110001 *
b01101101 +
#1117
0#
#1118
1#
b01101111 *
b01101111 +
#1119
0#
#1120
1#
b01110000 *
b01110001 +
#1121
0#
#1122
1#
b01101111 *
b01101111 +
#1123
0#
#1124
1#
b01101011 *
b01110000 +
#1125
0#
#1126
1#
b01101010 *
b01101111 +
#1127
0#
#1128
1#
b01101011 +
#1129
0#
#1130
1#
b01101000 *
b01101010 +
#1131
0#
#1132
1#
b01101010 *
#1133
0#
#1134
1#
b01101100 *
b01101000 +
#1135
0#
#1136
1#
b01101101 *
b01101010 +
#1137
0#
#1138
1#
b01101100 +
#1139
0#
#1140
1#
b01110000 *
b01101101 +
#1141
0#
#1142
1#
b01101111 *
#1143
0#
#1144
1#
b01110001 *
b01110000 +
#1145
0#
#1146
1#
b01101100 *
b01101111 +
#1147
0#
#1148
1#
b01101110 *
b01110001 +
#1149
0#
#1150
1#
b01101011 *
b01101100 +
#1151
0#
#1152
1#
b01101110 *
b01101110 +
#1153
0#
#1154
1#
b01101100 *
b01101011 +
#1155
0#
#1156
1#
b01110000 *
b01101110 +
#1157
0#
#1158
1#
b01110001 *
b01101100 +
#1159
0#
#1160
1#
b01101111 *
b01110000 +
#1161
0#
#1162
1#
b01110000 *
b01110001 +
#1163
0#
#1164
1#
b01101101 *
b01101111 +
#1165
0#
#1166
1#
b01101110 *
b01110000 +
#1167
0#
#1168
1#
b01101100 *
b01101101 +
#1169
0#
#1170
1#
b01101011 *
b01101110 +
#1171
0#
#1172
1#
b01101100 +
#1173
0#
#1174
1#
b01101010 *
b01101011 +
#1175
0#
#1176
1#
b01100111 *
#1177
0#
#1178
1#
b01101010 *
b01101010 +
#1179
0#
#1180
1#
b01100111 +
#1181
0#
#1182
1#
b01101001 *
b01101010 +
#1183
0#
#1184
1#
b01101011 *
#1185
0#
#1186
1#
b01101001 +
#1187
0#
#1188
1#
b01101001 *
b01101011 +
#1189
0#
#1190
1#
b01101000 *
#1191
0#
#1192
1#
b01100110 *
b01101001 +
#1193
0#
#1194
1#
b01101000 +
#1195
0#
#1196
1#
b01100111 *
b01100110 +
#1197
0#
#1198
1#
b01100110 *
#1199
0#
#1200
1#
b01100111 +
#1201
0#
#1202
1#
b01100101 *
b01100110 +
#1203
0#
#1204
1#
b01100111 *
#1205
0#
#1206
1#
b01100101 +
#1207
0#
#1208
1#
b01101001 *
b01100111 +
#1209
0#
#1210
1#
b01101011 *
#1211
0#
#1212
1#
b01100110 *
b01101001 +
#1213
0#
#1214
1#
b01101001 *
b01101011 +
#1215
0#
#1216
1#
b01101010 *
b01100110 +
#1217
0#
#1218
1#
b01101000 *
b01101001 +
#1219
0#
#1220
1#
b01101001 *
b01101010 +
#1221
0#
#1222
1#
b01101000 *
b01101000 +
#1223
0#
#1224
1#
b01101100 *
b01101001 +
#1225
0#
#1226
1#
b01101000 *
b01101000 +
#1227
0#
#1228
1#
b01101010 *
b01101100 +
#1229
0#
#1230
1#
b01101001 *
b01101000 +
#1231
0#
#1232
1#
b01101010 +
#1233
0#
#1234
1#
b01101010 *
b01101001 +
#1235
0#
#1236
1#
b01101001 *
#1237
0#
#1238
1#
b01101100 *
b01101010 +
#1239
0#
#1240
1#
b01100111 *
b01101001 +
#1241
0#
#1242
1#
b01100101 *
b01101100 +
#1243
0#
#1244
1#
b01100111 +
#1245
0#
#1246
1#
b01100100 *
b01100101 +
#1247
0#
#1248
1#
b01100011 *
#1249
0#
#1250
1#
b01100100 *
b01100100 +
#1251
0#
#1252
1#
b01100011 +
#1253
0#
#1254
1#
b01100010 *
b01100100 +
#1255
0#
#1256
1#
b01100100 *
#1257
0#
#1258
1#
b01100110 *
b01100010 +
#1259
0#
#1260
1#
b01100100 *
b01100100 +
#1261
0#
#1262
1#
b01100110 +
#1263
0#
#1264
1#
b01100101 *
b01100100 +
#1265
0#
#1266
1#
b01100011 *
#1267
0#
#1268
1#
b01100110 *
b01100101 +
#1269
0#
#1270
1#
b01100011 +
#1271
0#
#1272
1#
b01101000 *
b01100110 +
#1273
0#
#1274
1#
b01101001 *
#1275
0#
#1276
1#
b01101010 *
b01101000 +
#1277
0#
#1278
1#
b01101011 *
b01101001 +
#1279
0#
#1280
1#
b01101010 +
#1281
0#
#1282
1#
b01101001 *
b01101011 +
#1283
0#
#1284
1#
#1285
0#
#1286
1#
b01100111 *
b01101001 +
#1287
0#
#1288
1#
b01101001 *
#1289
0#
#1290
1#
b01100111 *
b01100111 +
#1291
0#
